declaredata_fuse/__init__.py
declaredata_fuse/column.py
declaredata_fuse/column_abc.py
declaredata_fuse/column_alias.py
declaredata_fuse/column_coalesce.py
declaredata_fuse/column_filter.py
declaredata_fuse/column_functional.py
declaredata_fuse/column_literal.py
declaredata_fuse/column_op.py
declaredata_fuse/column_or_name.py
declaredata_fuse/dataframe.py
declaredata_fuse/functions.py
declaredata_fuse/grouped.py
declaredata_fuse/py.typed
declaredata_fuse/row.py
declaredata_fuse/session.py
declaredata_fuse/window.py
declaredata_fuse/dataframe_impl/__init__.py
declaredata_fuse/dataframe_impl/collect.py
declaredata_fuse/dataframe_impl/drop.py
declaredata_fuse/dataframe_impl/join.py
declaredata_fuse/dataframe_impl/py.typed
declaredata_fuse/dataframe_impl/select.py
declaredata_fuse/dataframe_impl/sort.py
declaredata_fuse/proto/__init__.py
declaredata_fuse/proto/py.typed
declaredata_fuse/proto/sds_pb2.py
declaredata_fuse/proto/sds_pb2.pyi
declaredata_fuse/proto/sds_pb2_grpc.py
declaredata_fuse/proto/sds_pb2_grpc.pyi
declaredata_fuse/tests/dataframe_column_test.py
declaredata_fuse/tests/dataframe_group_test.py
declaredata_fuse/tests/filter_test.py
declaredata_fuse-0.1.8.dist-info/METADATA
declaredata_fuse-0.1.8.dist-info/WHEEL
declaredata_fuse-0.1.8.dist-info/RECORD
