Metadata-Version: 2.4
Name: declaredata_fuse
Version: 0.1.8
Summary: PySpark-compatible Python client for the DeclareData Fuse Server, a blazing fast drop-in data processing engine and alternative to Spark.
Author-email: Aaron Schlesinger <aaron@ecomaz.net>
Requires-Python: >=3.10
Requires-Dist: grpc-stubs>=1.53
Requires-Dist: grpcio>=1.67
Requires-Dist: protobuf>=5.28
Requires-Dist: pytest>=8.3.4
Requires-Dist: types-protobuf>=5.29.1.20241207
